DesktopScoreViewer/GameWindow.py
DesktopScoreViewer/MenuWindow.py
DesktopScoreViewer/ScoreWindow.py
DesktopScoreViewer/__init__.py
DesktopScoreViewer/__main__.py
DesktopScoreViewer-2.0.0.dist-info/METADATA
DesktopScoreViewer-2.0.0.dist-info/WHEEL
DesktopScoreViewer-2.0.0.dist-info/top_level.txt
DesktopScoreViewer-2.0.0.dist-info/RECORD
