Metadata-Version: 2.1
Name: DesktopScoreViewer
Version: 2.0.0
Summary: Gathers live MLB game scores and data and displays them on a mini GUI on the top right corner of the screen
Home-page: https://github.com/JosephJ12/DesktopScoreViewer
Author: Joseph Jung
Author-email: josephjung12@gmail.com
License: MIT
Platform: UNKNOWN
Classifier: License :: OSI Approved :: MIT License
Classifier: Programming Language :: Python :: 3
Classifier: Programming Language :: Python :: 3.7
Requires-Dist: wxPython
Requires-Dist: bs4
Requires-Dist: selenium
Requires-Dist: lxml
